setup.cfg
setup.py
flask_dev_mark/__init__.py
flask_dev_mark/middleware.py
flask_dev_mark_middleware.egg-info/PKG-INFO
flask_dev_mark_middleware.egg-info/SOURCES.txt
flask_dev_mark_middleware.egg-info/dependency_links.txt
flask_dev_mark_middleware.egg-info/requires.txt
flask_dev_mark_middleware.egg-info/top_level.txt
tests/__init__.py
tests/test_dev_mark.py