Metadata-Version: 1.0
Name: flask-dev-mark-middleware
Version: 0.0.1
Summary: Show dev mark on flask app
Home-page: https://github.com/simota/flask-dev-mark.git
Author: simota
Author-email: simota@me.com
License: MIT
Keywords: flask-dev-mark
Platform: UNKNOWN
